Metadata-Version: 2.1
Name: dataclass-jsonable
Version: 0.0.12
Summary: Simple and flexible conversions between dataclasses and jsonable dictionaries.
Home-page: https://github.com/hit9/dataclass-jsonable
Author: hit9
Author-email: hit9@icloud.com
License: BSD
Keywords: dataclasses,json,jsonable
Platform: UNKNOWN
Requires-Python: >=3.7
License-File: LICENSE-BSD3
